d2doc/__init__.py
d2doc/__main__.py
d2doc/__version__.py
d2doc/app.py
d2doc/d2doc.py
d2doc/translit.py
d2doc/parsers/__init__.py
d2doc/parsers/bsl.py
d2doc-0.9.2.dist-info/LICENSE
d2doc-0.9.2.dist-info/METADATA
d2doc-0.9.2.dist-info/WHEEL
d2doc-0.9.2.dist-info/entry_points.txt
d2doc-0.9.2.dist-info/top_level.txt
d2doc-0.9.2.dist-info/RECORD
