Metadata-Version: 2.1
Name: d2doc
Version: 0.9.2
Summary: Make technical documentstion from data sets
Home-page: https://github.com/brobots-corporation/d2doc
Author: Evgenii Alaev
Author-email: ev.alaev@yandex.ru
License: GPL-3.0
Project-URL: Bug Reports, https://github.com/brobots-corporation/d2doc/issues
Project-URL: Source, https://github.com/brobots-corporation/d2doc
Platform: UNKNOWN
Classifier: Development Status :: 5 - Production/Stable
Classifier: Intended Audience :: Developers
Classifier: Natural Language :: Russian
Classifier: Operating System :: OS Independent
Classifier: License :: OSI Approved :: GNU General Public License v3 (GPLv3)
Classifier: Programming Language :: Python :: 3.6
Classifier: Programming Language :: Python :: 3.7
Classifier: Programming Language :: Python :: 3.8
Classifier: Topic :: Software Development :: Libraries :: Python Modules
Requires-Python: >=3.6.0
Requires-Dist: Click (>=7.0)
Requires-Dist: Jinja2 (>=2.11.1)
Requires-Dist: MarkupSafe (>=1.1.1)
Requires-Dist: PyYAML (>=5.3xmltodict>=0.12.0)
